rtl/hcpu_pkg.vh
// ============================================================================
// HCPU Parameter Header — hcpu_pkg.vh
// Hijaiyyah Core Processing Unit — Verilog-2001 Compatible
// (c) 2026 HMCL — HM-28-v1.2-HC18D
// ============================================================================
//
// Usage: `include "hcpu_pkg.vh" at the top of every module.
// This file defines ALL shared constants: opcodes, register counts,
// memory map, field widths, and component indices.
//

`ifndef HCPU_PKG_VH
`define HCPU_PKG_VH

// ── Word widths ─────────────────────────────────────────────────
`define XLEN            32          // GPR width (bits)
`define ILEN            32          // Instruction width (bits)
`define COMP_W          8           // Codex component width (bits)
`define NDIM            18          // Codex dimensions
`define HREG_W          144         // H-Reg width: 18 × 8 = 144 bits
`define IMM_W           12          // Immediate field width

// ── Register counts ─────────────────────────────────────────────
`define GPR_COUNT       18          // R0–R17
`define HREG_COUNT      16          // H0–H15
`define STACK_DEPTH     256         // Stack entries (PUSH/POP)

// ── Master Table ────────────────────────────────────────────────
`define ROM_LETTERS     28          // 28 Hijaiyyah letters
`define ROM_ADDR_W      5           // ceil(log2(28)) = 5 bits

// ── Instruction field positions ─────────────────────────────────
// [31:24] OP  [23:20] DST  [19:16] S1  [15:12] S2  [11:0] IMM
`define OP_MSB          31
`define OP_LSB          24
`define DST_MSB         23
`define DST_LSB         20
`define S1_MSB          19
`define S1_LSB          16
`define S2_MSB          15
`define S2_LSB          12
`define IMM_MSB         11
`define IMM_LSB         0

// ── Code memory ─────────────────────────────────────────────────
`define CODE_ADDR_W     12          // 4096 instruction words
`define CODE_DEPTH      4096
// ── Data memory ─────────────────────────────────────────────────
`define DATA_ADDR_W     12          // 4096 × 32-bit words
`define DATA_DEPTH      4096

// ── Codex component indices (within 144-bit H-Reg) ──────────────
// Component[i] is at bits [8*i+7 : 8*i]
`define C_THETA         0           // Θ̂  — turning count
`define C_NA            1           // Na — nuqtah above
`define C_NB            2           // Nb — nuqtah below
`define C_ND            3           // Nd — nuqtah double
`define C_KP            4           // Kp — khatt primary
`define C_KX            5           // Kx — khatt extension
`define C_KS            6           // Ks — khatt secondary
`define C_KA            7           // Ka — khatt auxiliary
`define C_KC            8           // Kc — khatt closing
`define C_QP            9           // Qp — qaws primary
`define C_QX            10          // Qx — qaws extension
`define C_QS            11          // Qs — qaws secondary
`define C_QA            12          // Qa — qaws auxiliary
`define C_QC            13          // Qc — qaws closing
`define C_AN            14          // A_N — aggregate nuqtah
`define C_AK            15          // A_K — aggregate khatt
`define C_AQ            16          // A_Q — aggregate qaws
`define C_PSI           17          // Ψ   — chi/psi

// ────────────────────────────────────────────────────────────────
// OPCODES — Tier 1 (Fase 1 FPGA)
// ────────────────────────────────────────────────────────────────

// System & Control (0x00–0x0F)
`define OP_NOP          8'h00
`define OP_HALT         8'h01
`define OP_MOV          8'h03       // DST ← S1
`define OP_MOVI         8'h04       // DST ← zero_ext(IMM)

// Arithmetic & Logic (0x10–0x1F)
`define OP_ADD          8'h10       // DST ← S1 + S2
`define OP_ADDI         8'h11       // DST ← S1 + sign_ext(IMM)
`define OP_SUB          8'h12       // DST ← S1 - S2
`define OP_MUL          8'h14       // DST ← S1 × S2 (lower 32)

// Compare & Branch (0x20–0x2F)
`define OP_CMP          8'h20       // set FLAGS from S1 - S2
`define OP_CMPI         8'h21       // set FLAGS from S1 - sign_ext(IMM)
`define OP_JMP          8'h22       // PC ← zero_ext(IMM)
`define OP_JEQ          8'h23       // if Z=1: PC ← PC + sign_ext(IMM)
`define OP_JNE          8'h24       // if Z=0: PC ← PC + sign_ext(IMM)
`define OP_JGD          8'h29       // if G=1: PC ← PC + sign_ext(IMM)
`define OP_JNGD         8'h2A       // if G=0: PC ← PC + sign_ext(IMM)

// Memory (0x30–0x3F)
`define OP_PUSH         8'h32       // stack ← S1
`define OP_POP          8'h33       // DST ← stack

// Codex Operations — Hybit Native (0x40–0x5F)
`define OP_HLOAD        8'h40       // H[DST] ← ROM[IMM]  (letter index 1–28)
`define OP_HCADD        8'h42       // H[DST] ← H[S1] + H[S2]  (18×add)
`define OP_HGRD         8'h60       // Guard G1–G4,T1–T2 on H[S1] → GUARD flag
`define OP_HNRM2        8'h06       // GPR[DST] ← ‖H[S1]‖²₁₄
`define OP_HDIST        8'h07       // GPR[DST] ← ‖H[S1]−H[S2]‖²₁₄

// I/O (0xA0–0xAF)
`define OP_PRINT        8'hA0       // UART print GPR[S1] as decimal

// Unimplemented → trap
`define OP_HALT_ERR     8'hFF       // Halt with error (unimplemented opcode)

// ── FLAGS bit positions ─────────────────────────────────────────
`define FLAG_G          0           // GUARD pass
`define FLAG_Z          1           // ZERO
`define FLAG_O          2           // OVERFLOW
`define FLAG_LT         3           // Less-than (signed)

// ── UART default ────────────────────────────────────────────────
`define UART_BAUD       115200
`define SYS_CLK_HZ     50_000_000  // 50 MHz system clock

`endif // HCPU_PKG_VH

rtl/hcpu_rom.v
// ============================================================================
// HCPU Master Table ROM — hcpu_rom.v
// 28 letters × 18 components × 8 bits = 28 × 144-bit entries
// Pre-unpacked from hm28.rom for single-cycle HLOAD
// (c) 2026 HMCL — HM-28-v1.2-HC18D
// ============================================================================
//
// Data source: data/hm28.json (SHA-256 sealed)
// Component layout: comp[i] = data_out[8*i +: 8]
//   comp[0]=Θ̂, comp[1]=Na, ..., comp[17]=Ψ
//
// Usage: addr = letter index (1–28), data_out = 144-bit codex vector
// Combinational read (no clock needed) for single-cycle HLOAD.
//

`include "hcpu_pkg.vh"

module hcpu_rom (
    input  wire [`ROM_ADDR_W-1:0]  addr,       // letter index (1–28)
    output reg  [`HREG_W-1:0]      data_out,   // 144-bit codex vector
    output reg                     valid       // 1 if addr in [1,28]
);

    // Component packing macro: {comp[17], comp[16], ..., comp[1], comp[0]}
    // So comp[i] = data_out[8*i +: 8]

    always @(*) begin
        valid = 1'b1;
        case (addr)
            // ── Index 1: Alif (ا) ──
            //  [Θ̂=0, Na=0, Nb=0, Nd=0, Kp=1, Kx=0, Ks=0, Ka=0, Kc=0,
            //   Qp=0, Qx=0, Qs=0, Qa=0, Qc=0, AN=0, AK=1, AQ=0, Ψ=0]
            5'd1:  data_out = {8'd0,8'd0,8'd1,8'd0,8'd0,8'd0,8'd0,8'd0,
                               8'd0,8'd0,8'd0,8'd0,8'd0,8'd1,8'd0,8'd0,
                               8'd0,8'd0};

            // ── Index 2: Ba (ب) ──
            //  [2,0,0,1,0,1,0,0,0,1,0,0,0,0,1,1,1,0]
            5'd2:  data_out = {8'd0,8'd1,8'd1,8'd1,8'd0,8'd0,8'd0,8'd0,
                               8'd1,8'd0,8'd0,8'd0,8'd1,8'd0,8'd1,8'd0,
                               8'd0,8'd2};

            // ── Index 3: Ta (ت) ──
            //  [2,2,0,0,0,1,0,0,0,1,0,0,0,0,2,1,1,0]
            5'd3:  data_out = {8'd0,8'd1,8'd1,8'd2,8'd0,8'd0,8'd0,8'd0,
                               8'd1,8'd0,8'd0,8'd0,8'd1,8'd0,8'd0,8'd0,
                               8'd2,8'd2};

            // ── Index 4: Tsa (ث) ──
            //  [2,3,0,0,0,1,0,0,0,1,0,0,0,0,3,1,1,0]
            5'd4:  data_out = {8'd0,8'd1,8'd1,8'd3,8'd0,8'd0,8'd0,8'd0,
                               8'd1,8'd0,8'd0,8'd0,8'd1,8'd0,8'd0,8'd0,
                               8'd3,8'd2};

            // ── Index 5: Jim (ج) ──
            //  [3,0,1,0,0,1,0,0,0,1,0,0,0,0,1,1,1,0]
            5'd5:  data_out = {8'd0,8'd1,8'd1,8'd1,8'd0,8'd0,8'd0,8'd0,
                               8'd1,8'd0,8'd0,8'd0,8'd1,8'd0,8'd0,8'd1,
                               8'd0,8'd3};

            // ── Index 6: Ha (ح) ──
            //  [3,0,0,0,0,1,0,0,0,1,0,0,0,0,0,1,1,0]
            5'd6:  data_out = {8'd0,8'd1,8'd1,8'd0,8'd0,8'd0,8'd0,8'd0,
                               8'd1,8'd0,8'd0,8'd0,8'd1,8'd0,8'd0,8'd0,
                               8'd0,8'd3};

            // ── Index 7: Kha (خ) ──
            //  [3,1,0,0,0,1,0,0,0,1,0,0,0,0,1,1,1,0]
            5'd7:  data_out = {8'd0,8'd1,8'd1,8'd1,8'd0,8'd0,8'd0,8'd0,
                               8'd1,8'd0,8'd0,8'd0,8'd1,8'd0,8'd0,8'd0,
                               8'd1,8'd3};

            // ── Index 8: Dal (د) ──
            //  [1,0,0,0,0,0,0,0,0,0,0,0,1,0,0,0,1,0]
            5'd8:  data_out = {8'd0,8'd1,8'd0,8'd0,8'd0,8'd1,8'd0,8'd0,
                               8'd0,8'd0,8'd0,8'd0,8'd0,8'd0,8'd0,8'd0,
                               8'd0,8'd1};

            // ── Index 9: Dzal (ذ) ──
            //  [1,1,0,0,0,0,0,0,0,0,0,0,1,0,1,0,1,0]
            5'd9:  data_out = {8'd0,8'd1,8'd0,8'd1,8'd0,8'd1,8'd0,8'd0,
                               8'd0,8'd0,8'd0,8'd0,8'd0,8'd0,8'd0,8'd0,
                               8'd1,8'd1};

            // ── Index 10: Ra (ر) ──
            //  [1,0,0,0,0,0,0,0,0,0,0,1,0,0,0,0,1,0]
            5'd10: data_out = {8'd0,8'd1,8'd0,8'd0,8'd0,8'd0,8'd1,8'd0,
                               8'd0,8'd0,8'd0,8'd0,8'd0,8'd0,8'd0,8'd0,
                               8'd0,8'd1};

            // ── Index 11: Zay (ز) ──
            //  [1,1,0,0,0,0,0,0,0,0,0,1,0,0,1,0,1,0]
            5'd11: data_out = {8'd0,8'd1,8'd0,8'd1,8'd0,8'd0,8'd1,8'd0,
                               8'd0,8'd0,8'd0,8'd0,8'd0,8'd0,8'd0,8'd0,
                               8'd1,8'd1};

            // ── Index 12: Sin (س) ──
            //  [4,0,0,0,0,0,0,0,0,1,2,0,0,0,0,0,3,0]
            5'd12: data_out = {8'd0,8'd3,8'd0,8'd0,8'd0,8'd0,8'd0,8'd2,
                               8'd1,8'd0,8'd0,8'd0,8'd0,8'd0,8'd0,8'd0,
                               8'd0,8'd4};

            // ── Index 13: Syin (ش) ──
            //  [4,3,0,0,0,0,0,0,0,1,2,0,0,0,3,0,3,0]
            5'd13: data_out = {8'd0,8'd3,8'd0,8'd3,8'd0,8'd0,8'd0,8'd2,
                               8'd1,8'd0,8'd0,8'd0,8'd0,8'd0,8'd0,8'd0,
                               8'd3,8'd4};

            // ── Index 14: Shad (ص) ──
            //  [6,0,0,0,0,0,0,0,0,1,0,0,0,1,0,0,2,0]
            5'd14: data_out = {8'd0,8'd2,8'd0,8'd0,8'd1,8'd0,8'd0,8'd0,
                               8'd1,8'd0,8'd0,8'd0,8'd0,8'd0,8'd0,8'd0,
                               8'd0,8'd6};

            // ── Index 15: Dhad (ض) ──
            //  [6,1,0,0,0,0,0,0,0,1,0,0,0,1,1,0,2,0]
            5'd15: data_out = {8'd0,8'd2,8'd0,8'd1,8'd1,8'd0,8'd0,8'd0,
                               8'd1,8'd0,8'd0,8'd0,8'd0,8'd0,8'd0,8'd0,
                               8'd1,8'd6};

            // ── Index 16: Tha (ط) ──
            //  [4,0,0,0,0,0,0,1,0,0,0,0,0,1,0,1,1,0]
            5'd16: data_out = {8'd0,8'd1,8'd1,8'd0,8'd1,8'd0,8'd0,8'd0,
                               8'd0,8'd0,8'd1,8'd0,8'd0,8'd0,8'd0,8'd0,
                               8'd0,8'd4};

            // ── Index 17: Zha (ظ) ──
            //  [4,1,0,0,0,0,0,1,0,0,0,0,0,1,1,1,1,0]
            5'd17: data_out = {8'd0,8'd1,8'd1,8'd1,8'd1,8'd0,8'd0,8'd0,
                               8'd0,8'd0,8'd1,8'd0,8'd0,8'd0,8'd0,8'd0,
                               8'd1,8'd4};

            // ── Index 18: Ain (ع) ──
            //  [3,0,0,0,0,0,0,0,0,1,1,0,0,0,0,0,2,0]
            5'd18: data_out = {8'd0,8'd2,8'd0,8'd0,8'd0,8'd0,8'd0,8'd1,
                               8'd1,8'd0,8'd0,8'd0,8'd0,8'd0,8'd0,8'd0,
                               8'd0,8'd3};

            // ── Index 19: Ghain (غ) ──
            //  [3,1,0,0,0,0,0,0,0,1,1,0,0,0,1,0,2,0]
            5'd19: data_out = {8'd0,8'd2,8'd0,8'd1,8'd0,8'd0,8'd0,8'd1,
                               8'd1,8'd0,8'd0,8'd0,8'd0,8'd0,8'd0,8'd0,
                               8'd1,8'd3};

            // ── Index 20: Fa (ف) ──
            //  [5,1,0,0,0,1,0,0,0,1,0,0,0,1,1,1,2,0]
            5'd20: data_out = {8'd0,8'd2,8'd1,8'd1,8'd1,8'd0,8'd0,8'd0,
                               8'd1,8'd0,8'd0,8'd0,8'd1,8'd0,8'd0,8'd0,
                               8'd1,8'd5};

            // ── Index 21: Qaf (ق) ──
            //  [6,2,0,0,0,0,0,0,0,1,0,0,0,1,2,0,2,0]
            5'd21: data_out = {8'd0,8'd2,8'd0,8'd2,8'd1,8'd0,8'd0,8'd0,
                               8'd1,8'd0,8'd0,8'd0,8'd0,8'd0,8'd0,8'd0,
                               8'd2,8'd6};

            // ── Index 22: Kaf (ك) ──
            //  [2,0,0,0,0,0,0,0,1,0,0,0,0,0,0,1,0,1]
            5'd22: data_out = {8'd1,8'd0,8'd1,8'd0,8'd0,8'd0,8'd0,8'd0,
                               8'd0,8'd1,8'd0,8'd0,8'd0,8'd0,8'd0,8'd0,
                               8'd0,8'd2};

            // ── Index 23: Lam (ل) ──
            //  [1,0,0,0,0,1,0,0,0,1,0,0,0,0,0,1,1,0]
            5'd23: data_out = {8'd0,8'd1,8'd1,8'd0,8'd0,8'd0,8'd0,8'd0,
                               8'd1,8'd0,8'd0,8'd0,8'd1,8'd0,8'd0,8'd0,
                               8'd0,8'd1};

            // ── Index 24: Mim (م) ──
            //  [4,0,0,0,0,0,0,0,1,0,0,0,0,1,0,1,1,0]
            5'd24: data_out = {8'd0,8'd1,8'd1,8'd0,8'd1,8'd0,8'd0,8'd0,
                               8'd0,8'd1,8'd0,8'd0,8'd0,8'd0,8'd0,8'd0,
                               8'd0,8'd4};

            // ── Index 25: Nun (ن) ──
            //  [2,1,0,0,0,1,0,0,0,1,0,0,0,0,1,1,1,0]
            5'd25: data_out = {8'd0,8'd1,8'd1,8'd1,8'd0,8'd0,8'd0,8'd0,
                               8'd1,8'd0,8'd0,8'd0,8'd1,8'd0,8'd0,8'd0,
                               8'd1,8'd2};

            // ── Index 26: Waw (و) ──
            //  [5,0,0,0,0,0,0,0,0,0,0,1,0,1,0,0,2,0]
            5'd26: data_out = {8'd0,8'd2,8'd0,8'd0,8'd1,8'd0,8'd1,8'd0,
                               8'd0,8'd0,8'd0,8'd0,8'd0,8'd0,8'd0,8'd0,
                               8'd0,8'd5};

            // ── Index 27: Haa (هـ) ──
            //  [8,0,0,0,0,0,0,0,1,0,0,0,0,2,0,1,2,0]
            5'd27: data_out = {8'd0,8'd2,8'd1,8'd0,8'd2,8'd0,8'd0,8'd0,
                               8'd0,8'd1,8'd0,8'd0,8'd0,8'd0,8'd0,8'd0,
                               8'd0,8'd8};

            // ── Index 28: Ya (ي) ──
            //  [3,0,0,2,0,0,0,0,0,1,1,0,0,0,2,0,2,0]
            5'd28: data_out = {8'd0,8'd2,8'd0,8'd2,8'd0,8'd0,8'd0,8'd1,
                               8'd1,8'd0,8'd0,8'd0,8'd0,8'd0,8'd2,8'd0,
                               8'd0,8'd3};

            default: begin
                data_out = {`HREG_W{1'b0}};
                valid    = 1'b0;
            end
        endcase
    end

endmodule

rtl/hcpu_guard.v
// ============================================================================
// HCPU Guard Checker — hcpu_guard.v
// Hardware implementation of G1–G4 structural guards + T1–T2 topology
// Single-cycle, fully combinational — sets GUARD flag in O(1)
// (c) 2026 HMCL — HM-28-v1.2-HC18D
// ============================================================================
//
// Guard checks (from Bab I, Matematika Hijaiyyah):
//   G1: A_N = Na + Nb + Nd
//   G2: A_K = Kp + Kx + Ks + Ka + Kc
//   G3: A_Q = Qp + Qx + Qs + Qa + Qc
//   G4: ρ = Θ̂ − U ≥ 0  where U = Qx + Qs + Qa + 4×Qc
//   T1: Ks > 0  ⇒  Qc ≥ 1
//   T2: Kc > 0  ⇒  Qc ≥ 1
//
// All checks take one cycle. Result is a single PASS/FAIL bit.
//

`include "hcpu_pkg.vh"

module hcpu_guard (
    input  wire [`HREG_W-1:0]  vec,         // 144-bit codex vector
    output wire                guard_pass,  // 1 = all guards pass
    output wire                g1_pass,
    output wire                g2_pass,
    output wire                g3_pass,
    output wire                g4_pass,
    output wire                t1_pass,
    output wire                t2_pass
);

    // ── Extract components ──────────────────────────────────────
    wire [7:0] theta = vec[8*`C_THETA +: 8];  // Θ̂
    wire [7:0] na    = vec[8*`C_NA    +: 8];   // Na
    wire [7:0] nb    = vec[8*`C_NB    +: 8];   // Nb
    wire [7:0] nd    = vec[8*`C_ND    +: 8];   // Nd
    wire [7:0] kp    = vec[8*`C_KP    +: 8];   // Kp
    wire [7:0] kx    = vec[8*`C_KX    +: 8];   // Kx
    wire [7:0] ks    = vec[8*`C_KS    +: 8];   // Ks
    wire [7:0] ka    = vec[8*`C_KA    +: 8];   // Ka
    wire [7:0] kc    = vec[8*`C_KC    +: 8];   // Kc
    wire [7:0] qp    = vec[8*`C_QP    +: 8];   // Qp
    wire [7:0] qx    = vec[8*`C_QX    +: 8];   // Qx
    wire [7:0] qs    = vec[8*`C_QS    +: 8];   // Qs
    wire [7:0] qa    = vec[8*`C_QA    +: 8];   // Qa
    wire [7:0] qc    = vec[8*`C_QC    +: 8];   // Qc
    wire [7:0] a_n   = vec[8*`C_AN    +: 8];   // A_N
    wire [7:0] a_k   = vec[8*`C_AK    +: 8];   // A_K
    wire [7:0] a_q   = vec[8*`C_AQ    +: 8];   // A_Q

    // ── G1: A_N = Na + Nb + Nd ──────────────────────────────────
    wire [9:0] sum_n = na + nb + nd;
    assign g1_pass = (a_n == sum_n[7:0]) && (sum_n[9:8] == 2'b00 || a_n == sum_n[7:0]);

    // ── G2: A_K = Kp + Kx + Ks + Ka + Kc ───────────────────────
    wire [10:0] sum_k = kp + kx + ks + ka + kc;
    assign g2_pass = (a_k == sum_k[7:0]);

    // ── G3: A_Q = Qp + Qx + Qs + Qa + Qc ───────────────────────
    wire [10:0] sum_q = qp + qx + qs + qa + qc;
    assign g3_pass = (a_q == sum_q[7:0]);

    // ── G4: ρ = Θ̂ − U ≥ 0 ──────────────────────────────────────
    // U = Qx + Qs + Qa + 4 × Qc
    wire [10:0] u_val = qx + qs + qa + ({qc, 2'b00});  // qc << 2 = 4*qc
    // ρ = Θ̂ − U (signed: need to check if theta >= U)
    assign g4_pass = (theta >= u_val[7:0]);

    // ── T1: Ks > 0 ⇒ Qc ≥ 1 ────────────────────────────────────
    assign t1_pass = (ks == 8'd0) || (qc >= 8'd1);

    // ── T2: Kc > 0 ⇒ Qc ≥ 1 (Kaf is an exception) ──────────────
    wire is_kaf = (theta == 8'd2 && a_k == 8'd1 && a_q == 8'd0 && kc == 8'd1);
    assign t2_pass = (kc == 8'd0) || (qc >= 8'd1) || is_kaf;

    // ── Combined result ─────────────────────────────────────────
    assign guard_pass = g1_pass & g2_pass & g3_pass & g4_pass
                      & t1_pass & t2_pass;

endmodule

rtl/tb/tb_guard.v
// ============================================================================
// Testbench: Guard Checker — tb_guard.v
// Verifies G1–G4, T1–T2 for all 28 letters + corruption injection
// (c) 2026 HMCL
// ============================================================================

`timescale 1ns/1ps
`include "hcpu_pkg.vh"

module tb_guard;

    reg  [`HREG_W-1:0] vec;
    wire guard_pass, g1, g2, g3, g4, t1, t2;

    hcpu_guard uut (
        .vec        (vec),
        .guard_pass (guard_pass),
        .g1_pass    (g1),
        .g2_pass    (g2),
        .g3_pass    (g3),
        .g4_pass    (g4),
        .t1_pass    (t1),
        .t2_pass    (t2)
    );

    // ROM for loading valid vectors
    reg  [`ROM_ADDR_W-1:0] rom_addr;
    wire [`HREG_W-1:0]     rom_data;
    wire                   rom_valid;

    hcpu_rom u_rom (
        .addr     (rom_addr),
        .data_out (rom_data),
        .valid    (rom_valid)
    );

    integer pass_count, fail_count;
    integer idx;

    initial begin
        $dumpfile("tb_guard.vcd");
        $dumpvars(0, tb_guard);

        pass_count = 0;
        fail_count = 0;

        $display("=== HCPU Guard Checker Verification ===");

        // ── Test 1: All 28 letters should PASS ──────────────────
        for (idx = 1; idx <= 28; idx = idx + 1) begin
            rom_addr = idx[4:0];
            #1;
            vec = rom_data;
            #1;
            if (guard_pass) begin
                $display("PASS: Letter %0d — all guards pass", idx);
                pass_count = pass_count + 1;
            end else begin
                $display("FAIL: Letter %0d — G1=%b G2=%b G3=%b G4=%b T1=%b T2=%b",
                         idx, g1, g2, g3, g4, t1, t2);
                fail_count = fail_count + 1;
            end
        end

        // ── Test 2: G1 corruption (break A_N) ───────────────────
        // Load Ba (index 2), corrupt A_N component
        rom_addr = 5'd2; #1;
        vec = rom_data;
        vec[8*`C_AN +: 8] = 8'd99;  // A_N should be 1, set to 99
        #1;
        if (!g1) begin
            $display("PASS: G1 correctly detects A_N corruption");
            pass_count = pass_count + 1;
        end else begin
            $display("FAIL: G1 missed A_N corruption");
            fail_count = fail_count + 1;
        end

        // ── Test 3: G2 corruption (break A_K) ───────────────────
        rom_addr = 5'd2; #1;
        vec = rom_data;
        vec[8*`C_AK +: 8] = 8'd0;  // A_K should be 1, set to 0
        #1;
        if (!g2) begin
            $display("PASS: G2 correctly detects A_K corruption");
            pass_count = pass_count + 1;
        end else begin
            $display("FAIL: G2 missed A_K corruption");
            fail_count = fail_count + 1;
        end

        // ── Test 4: G3 corruption (break A_Q) ───────────────────
        rom_addr = 5'd2; #1;
        vec = rom_data;
        vec[8*`C_AQ +: 8] = 8'd99;  // A_Q should be 1, set to 99
        #1;
        if (!g3) begin
            $display("PASS: G3 correctly detects A_Q corruption");
            pass_count = pass_count + 1;
        end else begin
            $display("FAIL: G3 missed A_Q corruption");
            fail_count = fail_count + 1;
        end

        // ── Test 5: G4 corruption (ρ < 0) ──────────────────────
        // Load Haa (Θ̂=8), corrupt Qc to make U > Θ̂
        rom_addr = 5'd27; #1;
        vec = rom_data;
        vec[8*`C_QC +: 8] = 8'd10;  // 4*10=40 >> 8=Θ̂
        #1;
        if (!g4) begin
            $display("PASS: G4 correctly detects rho<0");
            pass_count = pass_count + 1;
        end else begin
            $display("FAIL: G4 missed rho<0 corruption");
            fail_count = fail_count + 1;
        end

        // ── Test 6: T1 violation (Ks>0 but Qc=0) ───────────────
        vec = {`HREG_W{1'b0}};
        vec[8*`C_KS +: 8] = 8'd1;  // Ks=1
        vec[8*`C_QC +: 8] = 8'd0;  // Qc=0 — violates T1
        #1;
        if (!t1) begin
            $display("PASS: T1 correctly detects Ks>0, Qc=0");
            pass_count = pass_count + 1;
        end else begin
            $display("FAIL: T1 missed violation");
            fail_count = fail_count + 1;
        end

        // ── Test 7: T2 violation (Kc>0 but Qc=0) ───────────────
        vec = {`HREG_W{1'b0}};
        vec[8*`C_KC +: 8] = 8'd2;  // Kc=2
        vec[8*`C_QC +: 8] = 8'd0;  // Qc=0 — violates T2
        #1;
        if (!t2) begin
            $display("PASS: T2 correctly detects Kc>0, Qc=0");
            pass_count = pass_count + 1;
        end else begin
            $display("FAIL: T2 missed violation");
            fail_count = fail_count + 1;
        end

        $display("========================================");
        $display("Guard Tests: %0d PASS, %0d FAIL", pass_count, fail_count);
        $display("========================================");

        if (fail_count > 0) $finish(1);
        else $finish(0);
    end

endmodule

rtl/tb/tb_guard.vcd
$date
	Fri Apr 10 09:09:13 2026
$end
$version
	Icarus Verilog
$end
$timescale
	1ps
$end
$scope module tb_guard $end
$var wire 1 ! t2 $end
$var wire 1 " t1 $end
$var wire 1 # rom_valid $end
$var wire 144 $ rom_data [143:0] $end
$var wire 1 % guard_pass $end
$var wire 1 & g4 $end
$var wire 1 ' g3 $end
$var wire 1 ( g2 $end
$var wire 1 ) g1 $end
$var reg 5 * rom_addr [4:0] $end
$var reg 144 + vec [143:0] $end
$var integer 32 , fail_count [31:0] $end
$var integer 32 - idx [31:0] $end
$var integer 32 . pass_count [31:0] $end
$scope module u_rom $end
$var wire 5 / addr [4:0] $end
$var reg 144 0 data_out [143:0] $end
$var reg 1 # valid $end
$upscope $end
$scope module uut $end
$var wire 1 ) g1_pass $end
$var wire 1 % guard_pass $end
$var wire 1 1 is_kaf $end
$var wire 1 " t1_pass $end
$var wire 1 ! t2_pass $end
$var wire 144 2 vec [143:0] $end
$var wire 11 3 u_val [10:0] $end
$var wire 8 4 theta [7:0] $end
$var wire 11 5 sum_q [10:0] $end
$var wire 10 6 sum_n [9:0] $end
$var wire 11 7 sum_k [10:0] $end
$var wire 8 8 qx [7:0] $end
$var wire 8 9 qs [7:0] $end
$var wire 8 : qp [7:0] $end
$var wire 8 ; qc [7:0] $end
$var wire 8 < qa [7:0] $end
$var wire 8 = nd [7:0] $end
$var wire 8 > nb [7:0] $end
$var wire 8 ? na [7:0] $end
$var wire 8 @ kx [7:0] $end
$var wire 8 A ks [7:0] $end
$var wire 8 B kp [7:0] $end
$var wire 8 C kc [7:0] $end
$var wire 8 D ka [7:0] $end
$var wire 1 & g4_pass $end
$var wire 1 ' g3_pass $end
$var wire 1 ( g2_pass $end
$var wire 8 E a_q [7:0] $end
$var wire 8 F a_n [7:0] $end
$var wire 8 G a_k [7:0] $end
$upscope $end
$upscope $end
$enddefinitions $end
$comment Show the parameter values. $end
$dumpall
$end
#0
$dumpvars
bx G
bx F
bx E
bx D
bx C
bx B
bx A
bx @
bx ?
bx >
bx =
bx <
bx ;
bx :
bx 9
bx 8
bx 7
bx 6
bx 5
bx 4
bx 3
bx 2
x1
b1000000000000000000000000000000000000000000000000000000000000000000000000000000000000000100000000000000000000000000000000 0
b1 /
b0 .
b1 -
b0 ,
bx +
b1 *
x)
x(
x'
x&
x%
b1000000000000000000000000000000000000000000000000000000000000000000000000000000000000000100000000000000000000000000000000 $
1#
x"
x!
$end
#1000
1%
1)
1!
1(
01
1'
1&
1"
b0 4
b0 6
b0 ?
b0 >
b0 =
b1 7
b1 B
b0 @
b0 A
b0 D
b0 C
b0 5
b0 :
b0 3
b0 8
b0 9
b0 <
b0 ;
b0 F
b1 G
b0 E
b1000000000000000000000000000000000000000000000000000000000000000000000000000000000000000100000000000000000000000000000000 +
b1000000000000000000000000000000000000000000000000000000000000000000000000000000000000000100000000000000000000000000000000 2
#2000
b100000001000000010000000000000000000000000000000000000001000000000000000000000000000000010000000000000001000000000000000000000010 $
b100000001000000010000000000000000000000000000000000000001000000000000000000000000000000010000000000000001000000000000000000000010 0
b10 *
b10 /
b10 -
b1 .
#3000
1%
1)
b10 4
b1 6
b1 =
b0 B
b1 7
b1 @
b1 5
b1 :
b1 F
1'
b1 E
b100000001000000010000000000000000000000000000000000000001000000000000000000000000000000010000000000000001000000000000000000000010 +
b100000001000000010000000000000000000000000000000000000001000000000000000000000000000000010000000000000001000000000000000000000010 2
#4000
b100000001000000100000000000000000000000000000000000000001000000000000000000000000000000010000000000000000000000000000001000000010 $
b100000001000000100000000000000000000000000000000000000001000000000000000000000000000000010000000000000000000000000000001000000010 0
b11 *
b11 /
b11 -
b10 .
#5000
1%
1)
b10 ?
b10 6
b0 =
b10 F
b100000001000000100000000000000000000000000000000000000001000000000000000000000000000000010000000000000000000000000000001000000010 +
b100000001000000100000000000000000000000000000000000000001000000000000000000000000000000010000000000000000000000000000001000000010 2
#6000
b100000001000000110000000000000000000000000000000000000001000000000000000000000000000000010000000000000000000000000000001100000010 $
b100000001000000110000000000000000000000000000000000000001000000000000000000000000000000010000000000000000000000000000001100000010 0
b100 *
b100 /
b100 -
b11 .
#7000
1%
1)
b11 6
b11 ?
b11 F
b100000001000000110000000000000000000000000000000000000001000000000000000000000000000000010000000000000000000000000000001100000010 +
b100000001000000110000000000000000000000000000000000000001000000000000000000000000000000010000000000000000000000000000001100000010 2
#8000
b100000001000000010000000000000000000000000000000000000001000000000000000000000000000000010000000000000000000000010000000000000011 $
b100000001000000010000000000000000000000000000000000000001000000000000000000000000000000010000000000000000000000010000000000000011 0
b101 *
b101 /
b101 -
b100 .
#9000
1%
1)
b11 4
b0 ?
b1 6
b1 >
b1 F
b100000001000000010000000000000000000000000000000000000001000000000000000000000000000000010000000000000000000000010000000000000011 +
b100000001000000010000000000000000000000000000000000000001000000000000000000000000000000010000000000000000000000010000000000000011 2
#10000
b100000001000000000000000000000000000000000000000000000001000000000000000000000000000000010000000000000000000000000000000000000011 $
b100000001000000000000000000000000000000000000000000000001000000000000000000000000000000010000000000000000000000000000000000000011 0
b110 *
b110 /
b110 -
b101 .
#11000
1%
1)
b0 6
b0 >
b0 F
b100000001000000000000000000000000000000000000000000000001000000000000000000000000000000010000000000000000000000000000000000000011 +
b100000001000000000000000000000000000000000000000000000001000000000000000000000000000000010000000000000000000000000000000000000011 2
#12000
b100000001000000010000000000000000000000000000000000000001000000000000000000000000000000010000000000000000000000000000000100000011 $
b100000001000000010000000000000000000000000000000000000001000000000000000000000000000000010000000000000000000000000000000100000011 0
b111 *
b111 /
b111 -
b110 .
#13000
1%
1)
b1 6
b1 ?
b1 F
b100000001000000010000000000000000000000000000000000000001000000000000000000000000000000010000000000000000000000000000000100000011 +
b100000001000000010000000000000000000000000000000000000001000000000000000000000000000000010000000000000000000000000000000100000011 2
#14000
b100000000000000000000000000000001000000000000000000000000000000000000000000000000000000000000000000000000000000000000000000000001 $
b100000000000000000000000000000001000000000000000000000000000000000000000000000000000000000000000000000000000000000000000000000001 0
b1000 *
b1000 /
b1000 -
b111 .
